{
  "kind": "collectionType",
  "collectionName": "donations",
  "info": {
    "singularName": "donation",
    "pluralName": "donations",
    "displayName": "donation"
  },
  "options": {
    "draftAndPublish": true
  },
  "pluginOptions": {},
  "attributes": {
    "Alimentos": {
      "type": "enumeration",
      "required": true,
      "default": "Arroz",
      "enum": [
        "Arroz",
        "Macarrao",
        "Feijao",
        "Oleo",
        "Sal",
        "Açucar"
      ]
    },
    "quantity": {
      "type": "string",
      "required": true
    },
    "expiration_date": {
      "type": "date"
    },
    "status_donation": {
      "type": "enumeration",
      "required": true,
      "default": "Pendente",
      "enum": [
        "Pendente",
        "Enviada",
        "Entregue"
      ]
    },
    "user": {
      "type": "relation",
      "relation": "manyToOne",
      "target": "plugin::users-permissions.user",
      "inversedBy": "donations"
    },
    "ong": {
      "type": "relation",
      "relation": "manyToOne",
      "target": "api::ong.ong",
      "inversedBy": "donations"
    }
  }
}
